[
	{
		"cat_slug": "eclectic-resonance",
		"projects": [
      {
				"slug": "eclectic-resonance-paradise",
				"status": "accepting",
				"percentage": "0",
				"duration": "00:00",
				"finished_tracks": "0",
				"deadline": "2025-03-23T23:59:59Z",
				"mastering": {
					"status": "pending",
					"engineer": "R-Man (Resonant Union)"
				},
				"artwork_comission": "sketching",
				"color": "#dbb458"
			},
			{
				"slug": "eclectic-resonance-escapism",
				"status": "accepting",
				"percentage": "0",
				"duration": "00:00",
				"finished_tracks": "0",
				"deadline": "2025-03-23T23:59:59Z",
				"mastering": {
					"status": "pending",
					"engineer": "malicent (Cursed Monastery / Sigillum Azoetia)"
				},
				"artwork_comission": "sketching",
				"color": "#68bd7d"
			},
			{
				"slug": "eclectic-resonance-uprising-3",
				"status": "accepting",
				"percentage": "0",
				"duration": "00:00",
				"finished_tracks": "0",
				"deadline": "2025-09-13T23:59:59Z",
				"mastering": {
					"status": "pending",
					"engineer": "TBD"
				},
				"artwork_comission": "pending",
				"color": "#6cc3b9"
			},
      {
				"slug": "eclectic-resonance-memories-2",
				"status": "accepting",
				"percentage": "0",
				"duration": "00:00",
				"finished_tracks": "0",
				"deadline": "2025-09-13T23:59:59Z",
				"mastering": {
					"status": "pending",
					"engineer": "TBD"
				},
				"artwork_comission": "pending",
				"color": "#f9c74f"
			},
			{
				"slug": "eclectic-resonance-detuned-alloy-2",
				"status": "accepting",
				"percentage": "0",
				"duration": "00:00",
				"finished_tracks": "0",
				"mastering": {
					"status": "pending",
					"engineer": "R-Man (Resonant Union)"
				},
				"artwork_comission": "pending",
				"color": "#9f1239"
			},
      {
				"slug": "eclectic-resonance-hollow-horizons-2",
				"status": "accepting",
				"percentage": "0",
				"duration": "00:00",
				"finished_tracks": "0",
				"mastering": {
					"status": "pending",
					"engineer": "TBD"
				},
				"artwork_comission": "pending",
				"color": "#000000"
			},
      {
				"slug":"eclectic-resonance-legendaria-2",
				"status": "accepting",
				"percentage": "0",
				"duration": "00:00",
				"finished_tracks": "0",
				"mastering": {
					"status": "pending",
					"engineer": "TBD"
				},
				"artwork_comission": "pending",
				"color": "#d44215"
			}
		]
	},
	{
		"cat_slug": "tribute-albums",
		"projects": [
			{
				"slug": "vanilla-parfait",
				"status": "accepting",
				"percentage": "0",
				"duration": "00:00",
				"finished_tracks": "0",
				"deadline": "2024-12-07T23:59:59Z",
				"mastering": {
					"status": "pending",
					"engineer": "R-Man (Resonant Union)"
				},
				"artwork_comission": "pending",
				"color": "#ceab82"
			},
			{
				"slug": "moonstruck-analogy-ii",
				"status": "accepting",
				"percentage": "0",
				"duration": "00:00",
				"finished_tracks": "0",
				"mastering": {
					"status": "pending",
					"engineer": "malicent (Cursed Monastery / Sigillum Azoetia)"
				},
				"artwork_comission": "pending",
				"color": "#fde68a"
			},
			{
				"slug": "fragments-of-gratitude-ii",
				"status": "accepting",
				"percentage": "5",
				"duration": "03:25",
				"finished_tracks": "1",
				"mastering": {
					"status": "pending",
					"engineer": "malicent (Cursed Monastery / Sigillum Azoetia)"
				},
				"artwork_comission": "pending",
				"color": "#7dd3fc"
			},
			{
				"slug": "katamania-2",
				"status": "accepting",
				"percentage": "0",
				"duration": "00:00",
				"finished_tracks": "0",
				"mastering": {
					"status": "pending",
					"engineer": "malicent (Cursed Monastery / Sigillum Azoetia)"
				},
				"artwork_comission": "pending",
				"color": "#f472b6"
			},			
			{
				"slug": "midnight-syndrome-2",
				"status": "accepting",
				"percentage": "0",
				"duration": "00:00",
				"finished_tracks": "0",
				"mastering": {
					"status": "pending",
					"engineer": "TBD"
				},
				"artwork_comission": "pending",
				"color": "#e94242"
			}
		]
	},
	{
		"cat_slug": "gensokyo-party",
		"projects": [
			{
				"slug": "gensokyo-party-6-border-in-stasis",
				"status": "accepting",
				"percentage": "30",
				"duration": "09:05",
				"finished_tracks": "2",
				"deadline": "2025-03-15T23:59:59Z",
				"mastering": {
					"status": "pending",
					"engineer": "blobdash"
				},
				"artwork_comission": "completed",
				"color": "#fda564"
			},
			{
				"slug": "moriya-barista-2",
				"status": "accepting",
				"percentage": "0",
				"duration": "00:00",
				"finished_tracks": "0",
				"mastering": {
					"status": "pending",
					"engineer": "R-Man (Resonant Union)"
				},
				"artwork_comission": "pending",
				"color": "#6ee7b7"
			},
			{
				"slug": "dj-koishi-2",
				"status": "accepting",
				"percentage": "0",
				"duration": "00:00",
				"finished_tracks": "0",
				"mastering": {
					"status": "pending",
					"engineer": "malicent (Cursed Monastery / Sigillum Azoetia)"
				},
				"artwork_comission": "pending",
				"color": "#65a30d"
			},
			{
				"slug": "gensokyo-party-vantablack-3",
				"status": "accepting",
				"percentage": "0",
				"duration": "00:00",
				"finished_tracks": "0",
				"mastering": {
					"status": "pending",
					"engineer": "TBD"
				},
				"artwork_comission": "pending",
				"color": "#fcbcda"
			}
		]
	}
]
